django_jsonfield_compat-0.4.4.dist-info/DESCRIPTION.rst
django_jsonfield_compat-0.4.4.dist-info/METADATA
django_jsonfield_compat-0.4.4.dist-info/RECORD
django_jsonfield_compat-0.4.4.dist-info/WHEEL
django_jsonfield_compat-0.4.4.dist-info/metadata.json
django_jsonfield_compat-0.4.4.dist-info/top_level.txt
jsonfield_compat/__init__.py
jsonfield_compat/compat.py
jsonfield_compat/convert.py
jsonfield_compat/fields.py
jsonfield_compat/forms.py
jsonfield_compat/util.py
