Metadata-Version: 1.1
Name: django-jsonfield-compat
Version: 0.4.4
Summary: Compatability layer between django-jsonfield and Django's native JSONField
Home-page: http://github.com/kbussell/django-jsonfield-compat/
Author: Keith Bussell
Author-email: kbussell@gmail.com
License: UNKNOWN
Platform: UNKNOWN
Classifier: Programming Language :: Python
Classifier: Programming Language :: Python :: 3
Classifier: License :: OSI Approved :: MIT License
Classifier: Operating System :: OS Independent
Classifier: Framework :: Django
